lktk/__init__.py
lktk/__main__.py
lktk/command.py
lktk/exception.py
lktk/formatter.py
lktk/lkml.lark
lktk/logger.py
lktk/parser.py
lktk/template.py
lktk-0.0.2.dist-info/METADATA
lktk-0.0.2.dist-info/WHEEL
lktk-0.0.2.dist-info/entry_points.txt
lktk-0.0.2.dist-info/RECORD
