Metadata-Version: 2.1
Name: lktk
Version: 0.0.2
Summary: 
Author: dr666m1
Author-email: skndr666m1@gmail.com
Requires-Python: >=3.11,<4.0
Classifier: Programming Language :: Python :: 3
Classifier: Programming Language :: Python :: 3.11
Requires-Dist: click (>=8.1.3,<9.0.0)
Requires-Dist: lark (>=1.1.5,<2.0.0)
Requires-Dist: shandy-sqlfmt (>=0.17.0,<0.18.0)
